{
	"configurations" : 
	[
		{
			"directories" : 
			[
				{
					"build" : ".",
					"jsonFile" : "directory-.-Debug-d0094a50bb2071803777.json",
					"minimumCMakeVersion" : 
					{
						"string" : "3.10.0"
					},
					"projectIndex" : 0,
					"source" : ".",
					"targetIndexes" : 
					[
						0
					]
				}
			],
			"name" : "Debug",
			"projects" : 
			[
				{
					"directoryIndexes" : 
					[
						0
					],
					"name" : "secure_comm_native",
					"targetIndexes" : 
					[
						0
					]
				}
			],
			"targets" : 
			[
				{
					"directoryIndex" : 0,
					"id" : "secure_comm_native::@6890427a1f51a3e7e1df",
					"jsonFile" : "target-secure_comm_native-Debug-ce659a808965f4c619e1.json",
					"name" : "secure_comm_native",
					"projectIndex" : 0
				}
			]
		}
	],
	"kind" : "codemodel",
	"paths" : 
	{
		"build" : "C:/ReGenesis/secure-comm/.cxx/Debug/1a2b5424/x86_64",
		"source" : "C:/ReGenesis/secure-comm/src/main/cpp"
	},
	"version" : 
	{
		"major" : 2,
		"minor" : 3
	}
}
